connectivity/Constants.py
connectivity/Exceptions.py
connectivity/FileMover.py
connectivity/FileSender.py
connectivity/MessageOrganizer.py
connectivity/__init__.py
connectivity/client/Client.py
connectivity/client/FileClient.py
connectivity/client/MessageClient.py
connectivity/client/__init__.py
connectivity/server/FileServer.py
connectivity/server/MessageServer.py
connectivity/server/Server.py
connectivity/server/__init__.py
connectivity-31.dist-info/LICENSE
connectivity-31.dist-info/METADATA
connectivity-31.dist-info/WHEEL
connectivity-31.dist-info/top_level.txt
connectivity-31.dist-info/RECORD
